{
  "templates": [
    {
      "id": "rail-vintage",
      "kind": "train",
      "title": "Vintage Rail",
      "headline": "RAIL PASSAGE TICKET",
      "accentHex": "#B44D35",
      "paperHex": "#F9F1E4",
      "fields": {
        "origin": "SHANGHAI",
        "destination": "HANGZHOU",
        "date": "22 MAY 2026",
        "time": "08:45",
        "seat": "CAR 03 / 12A",
        "gate": "7B",
        "className": "SECOND",
        "reference": "NO. A12-045"
      }
    },
    {
      "id": "rail-local",
      "kind": "train",
      "title": "Local Line",
      "headline": "LOCAL TRAIN TICKET",
      "accentHex": "#6F8A64",
      "paperHex": "#F4F4E8",
      "fields": {
        "origin": "SHENZHEN",
        "destination": "GUANGZHOU",
        "date": "23 MAY 2026",
        "time": "09:18",
        "seat": "05C",
        "gate": "A3",
        "className": "STANDARD",
        "reference": "RAIL 2305"
      }
    },
    {
      "id": "rail-sleeper",
      "kind": "train",
      "title": "Night Sleeper",
      "headline": "NIGHT RAIL PASS",
      "accentHex": "#384C70",
      "paperHex": "#EEF1F7",
      "fields": {
        "origin": "BEIJING",
        "destination": "XI'AN",
        "date": "28 MAY 2026",
        "time": "22:10",
        "seat": "BUNK 12",
        "gate": "9",
        "className": "SLEEPER",
        "reference": "NIGHT 891"
      }
    },
    {
      "id": "rail-metro",
      "kind": "train",
      "title": "Metro Ride",
      "headline": "CITY METRO PASS",
      "accentHex": "#D18B2F",
      "paperHex": "#FFF5DF",
      "fields": {
        "origin": "CENTRAL",
        "destination": "OLD TOWN",
        "date": "01 JUN 2026",
        "time": "18:05",
        "seat": "STAND",
        "gate": "LINE 2",
        "className": "SINGLE",
        "reference": "MTR 611"
      }
    },
    {
      "id": "rail-scenic",
      "kind": "train",
      "title": "Scenic Rail",
      "headline": "MOUNTAIN RAILWAY",
      "accentHex": "#496F58",
      "paperHex": "#F2F6EA",
      "fields": {
        "origin": "LUCERNE",
        "destination": "INTERLAKEN",
        "date": "03 JUN 2026",
        "time": "10:22",
        "seat": "PAN 04",
        "gate": "2",
        "className": "PANORAMA",
        "reference": "ALP 332"
      }
    },
    {
      "id": "rail-express",
      "kind": "train",
      "title": "Express",
      "headline": "HIGH SPEED EXPRESS",
      "accentHex": "#A63D40",
      "paperHex": "#F8F1ED",
      "fields": {
        "origin": "TOKYO",
        "destination": "KYOTO",
        "date": "05 JUN 2026",
        "time": "07:36",
        "seat": "12E",
        "gate": "14",
        "className": "RESERVED",
        "reference": "HSE 705"
      }
    },
    {
      "id": "air-boarding",
      "kind": "flight",
      "title": "Boarding Pass",
      "headline": "BOARDING PASS",
      "accentHex": "#2F6F8F",
      "paperHex": "#F3F7FA",
      "fields": {
        "origin": "SZX",
        "destination": "NRT",
        "date": "24 MAY 2026",
        "time": "13:20",
        "seat": "18A",
        "gate": "G12",
        "className": "ECONOMY",
        "reference": "FLIGHT TC 726"
      }
    },
    {
      "id": "air-luggage",
      "kind": "flight",
      "title": "Luggage Tag",
      "headline": "AIRLINE BAG TAG",
      "accentHex": "#587C9B",
      "paperHex": "#F6FAFC",
      "fields": {
        "origin": "SZX",
        "destination": "BKK",
        "date": "29 MAY 2026",
        "time": "16:35",
        "seat": "22F",
        "gate": "B08",
        "className": "ECONOMY",
        "reference": "BAG 0704"
      }
    },
    {
      "id": "air-retro",
      "kind": "flight",
      "title": "Retro Air",
      "headline": "SKY PASSAGE",
      "accentHex": "#A0644B",
      "paperHex": "#FFF4E8",
      "fields": {
        "origin": "HKG",
        "destination": "TPE",
        "date": "30 MAY 2026",
        "time": "11:05",
        "seat": "04A",
        "gate": "C16",
        "className": "BUSINESS",
        "reference": "SKY 156"
      }
    },
    {
      "id": "air-red-eye",
      "kind": "flight",
      "title": "Red Eye",
      "headline": "OVERNIGHT BOARDING",
      "accentHex": "#39435E",
      "paperHex": "#F0F1F7",
      "fields": {
        "origin": "LAX",
        "destination": "JFK",
        "date": "02 JUN 2026",
        "time": "23:55",
        "seat": "31C",
        "gate": "45A",
        "className": "ECONOMY",
        "reference": "TC 902"
      }
    },
    {
      "id": "air-lounge",
      "kind": "flight",
      "title": "Lounge Pass",
      "headline": "AIRPORT LOUNGE PASS",
      "accentHex": "#8C6A42",
      "paperHex": "#FBF2E4",
      "fields": {
        "origin": "DOH",
        "destination": "LOUNGE C",
        "date": "04 JUN 2026",
        "time": "06:10",
        "seat": "SOFA 08",
        "gate": "C21",
        "className": "ACCESS",
        "reference": "LNG 214"
      }
    },
    {
      "id": "air-seaplane",
      "kind": "flight",
      "title": "Seaplane",
      "headline": "ISLAND AIR TRANSFER",
      "accentHex": "#2D8B9B",
      "paperHex": "#EAF8F7",
      "fields": {
        "origin": "MALE",
        "destination": "ATOLL",
        "date": "08 JUN 2026",
        "time": "15:25",
        "seat": "06A",
        "gate": "DOCK 1",
        "className": "FLOAT",
        "reference": "SEA 808"
      }
    },
    {
      "id": "cinema-stub",
      "kind": "movie",
      "title": "Cinema Stub",
      "headline": "CINEMA TICKET",
      "accentHex": "#6D4C8D",
      "paperHex": "#FFF2D8",
      "fields": {
        "origin": "STUDIO 6",
        "destination": "MIDNIGHT SHOW",
        "date": "25 MAY 2026",
        "time": "21:30",
        "seat": "ROW F / 09",
        "gate": "HALL 2",
        "className": "ADMIT ONE",
        "reference": "NO. M88-109"
      }
    },
    {
      "id": "cinema-matinee",
      "kind": "movie",
      "title": "Matinee",
      "headline": "MATINEE ADMISSION",
      "accentHex": "#C4563F",
      "paperHex": "#FFF7E6",
      "fields": {
        "origin": "PALACE CINEMA",
        "destination": "AFTERNOON SHOW",
        "date": "24 MAY 2026",
        "time": "14:20",
        "seat": "ROW C / 06",
        "gate": "SCREEN 3",
        "className": "ADMIT ONE",
        "reference": "MAT 024"
      }
    },
    {
      "id": "cinema-premiere",
      "kind": "movie",
      "title": "Premiere",
      "headline": "PREMIERE NIGHT",
      "accentHex": "#2F2A35",
      "paperHex": "#F8EFD8",
      "fields": {
        "origin": "GRAND THEATRE",
        "destination": "OPENING NIGHT",
        "date": "26 MAY 2026",
        "time": "20:00",
        "seat": "BALCONY 12",
        "gate": "HALL 1",
        "className": "VIP",
        "reference": "PRM 618"
      }
    },
    {
      "id": "cinema-indie",
      "kind": "movie",
      "title": "Indie House",
      "headline": "ART HOUSE SCREENING",
      "accentHex": "#4A4F41",
      "paperHex": "#F4EBD6",
      "fields": {
        "origin": "BIJOU CINEMA",
        "destination": "ROOM 12",
        "date": "02 JUN 2026",
        "time": "19:10",
        "seat": "ROW D / 04",
        "gate": "SCREEN 1",
        "className": "INDIE",
        "reference": "ART 204"
      }
    },
    {
      "id": "cinema-open-air",
      "kind": "movie",
      "title": "Open Air",
      "headline": "OPEN AIR CINEMA",
      "accentHex": "#2F6B58",
      "paperHex": "#F0F7E9",
      "fields": {
        "origin": "PARK LAWN",
        "destination": "SUNSET FILM",
        "date": "06 JUN 2026",
        "time": "20:15",
        "seat": "BLANKET 7",
        "gate": "LAWN A",
        "className": "PICNIC",
        "reference": "OPEN 606"
      }
    },
    {
      "id": "cinema-film-fest",
      "kind": "movie",
      "title": "Film Fest",
      "headline": "FESTIVAL SCREENING",
      "accentHex": "#B76E50",
      "paperHex": "#FFF1E6",
      "fields": {
        "origin": "FEST HALL",
        "destination": "SHORTS A",
        "date": "09 JUN 2026",
        "time": "17:45",
        "seat": "ROW B / 11",
        "gate": "THEATRE 4",
        "className": "PASS",
        "reference": "FF 091"
      }
    },
    {
      "id": "ferry-keepsake",
      "kind": "ferry",
      "title": "Ferry Keepsake",
      "headline": "FERRY PASSAGE",
      "accentHex": "#2F7D70",
      "paperHex": "#EEF8F2",
      "fields": {
        "origin": "HONG KONG",
        "destination": "MACAU",
        "date": "26 MAY 2026",
        "time": "10:15",
        "seat": "DECK B / 21",
        "gate": "PIER 4",
        "className": "WINDOW",
        "reference": "SEA 04-221"
      }
    },
    {
      "id": "ferry-island",
      "kind": "ferry",
      "title": "Island Hop",
      "headline": "ISLAND FERRY PASS",
      "accentHex": "#4D8B93",
      "paperHex": "#EEF8F8",
      "fields": {
        "origin": "KOWLOON",
        "destination": "CHEUNG CHAU",
        "date": "27 MAY 2026",
        "time": "12:40",
        "seat": "OPEN DECK",
        "gate": "PIER 5",
        "className": "DAY PASS",
        "reference": "ISLE 527"
      }
    },
    {
      "id": "ferry-night",
      "kind": "ferry",
      "title": "Night Ferry",
      "headline": "NIGHT SEA PASSAGE",
      "accentHex": "#3D5364",
      "paperHex": "#F0F4F5",
      "fields": {
        "origin": "SHENZHEN",
        "destination": "ZHUHAI",
        "date": "31 MAY 2026",
        "time": "19:25",
        "seat": "CABIN 08",
        "gate": "PIER 2",
        "className": "CABIN",
        "reference": "SEA 312"
      }
    },
    {
      "id": "ferry-river",
      "kind": "ferry",
      "title": "River Cruise",
      "headline": "RIVER CRUISE PASS",
      "accentHex": "#345E6F",
      "paperHex": "#EDF6F6",
      "fields": {
        "origin": "PIER EAST",
        "destination": "OLD BRIDGE",
        "date": "02 JUN 2026",
        "time": "18:30",
        "seat": "DECK 2",
        "gate": "PIER 8",
        "className": "SUNSET",
        "reference": "RVR 230"
      }
    },
    {
      "id": "ferry-lake",
      "kind": "ferry",
      "title": "Lake Boat",
      "headline": "LAKE SHUTTLE TICKET",
      "accentHex": "#6C8B5D",
      "paperHex": "#F3F8ED",
      "fields": {
        "origin": "NORTH DOCK",
        "destination": "PINE ISLE",
        "date": "04 JUN 2026",
        "time": "09:50",
        "seat": "BENCH 6",
        "gate": "DOCK C",
        "className": "RETURN",
        "reference": "LAKE 404"
      }
    },
    {
      "id": "ferry-harbor",
      "kind": "ferry",
      "title": "Harbor Hop",
      "headline": "HARBOR WATERBUS",
      "accentHex": "#237A8C",
      "paperHex": "#EAF7FA",
      "fields": {
        "origin": "MARINA",
        "destination": "MUSEUM PIER",
        "date": "07 JUN 2026",
        "time": "13:05",
        "seat": "OPEN",
        "gate": "BAY 3",
        "className": "DAY",
        "reference": "HBR 713"
      }
    },
    {
      "id": "event-museum",
      "kind": "event",
      "title": "Museum",
      "headline": "MUSEUM ENTRY TICKET",
      "accentHex": "#7B5942",
      "paperHex": "#F7EFE2",
      "fields": {
        "origin": "CITY MUSEUM",
        "destination": "SPECIAL WING",
        "date": "01 JUN 2026",
        "time": "11:00",
        "seat": "ROOM 5",
        "gate": "EAST",
        "className": "ADMISSION",
        "reference": "MSM 101"
      }
    },
    {
      "id": "event-concert",
      "kind": "event",
      "title": "Concert",
      "headline": "LIVE CONCERT PASS",
      "accentHex": "#8E3F62",
      "paperHex": "#F9ECF2",
      "fields": {
        "origin": "ARENA",
        "destination": "NIGHT SET",
        "date": "03 JUN 2026",
        "time": "20:30",
        "seat": "SEC B / 18",
        "gate": "GATE 6",
        "className": "FLOOR",
        "reference": "LVE 338"
      }
    },
    {
      "id": "event-gallery",
      "kind": "event",
      "title": "Gallery",
      "headline": "GALLERY OPENING",
      "accentHex": "#4D5F74",
      "paperHex": "#F0F3F6",
      "fields": {
        "origin": "WHITE CUBE",
        "destination": "ROOM BLUE",
        "date": "05 JUN 2026",
        "time": "18:00",
        "seat": "STANDING",
        "gate": "NORTH",
        "className": "INVITE",
        "reference": "ART 550"
      }
    },
    {
      "id": "event-theme-park",
      "kind": "event",
      "title": "Theme Park",
      "headline": "THEME PARK DAY PASS",
      "accentHex": "#D26A3F",
      "paperHex": "#FFF2DD",
      "fields": {
        "origin": "SUN PARK",
        "destination": "ZONE A",
        "date": "07 JUN 2026",
        "time": "09:00",
        "seat": "ALL DAY",
        "gate": "MAIN",
        "className": "DAY PASS",
        "reference": "FUN 707"
      }
    },
    {
      "id": "event-food-fair",
      "kind": "event",
      "title": "Food Fair",
      "headline": "STREET FOOD FAIR",
      "accentHex": "#AF5F35",
      "paperHex": "#FFF5E8",
      "fields": {
        "origin": "MARKET ROW",
        "destination": "TASTING LANE",
        "date": "08 JUN 2026",
        "time": "12:00",
        "seat": "TABLE 4",
        "gate": "SOUTH",
        "className": "TASTING",
        "reference": "EAT 812"
      }
    },
    {
      "id": "event-heritage-tour",
      "kind": "event",
      "title": "Heritage Tour",
      "headline": "HERITAGE WALK PASS",
      "accentHex": "#6F6A43",
      "paperHex": "#F6F2DA",
      "fields": {
        "origin": "CLOCK TOWER",
        "destination": "OLD QUARTER",
        "date": "10 JUN 2026",
        "time": "16:20",
        "seat": "GROUP 2",
        "gate": "START",
        "className": "GUIDED",
        "reference": "WALK 210"
      }
    }
  ]
}
